{
  "bookings": [
    {
      "id": "BK001",
      "clientId": "CL001",
      "clientName": "Juan Martinez",
      "clientPhone": "(956) 555-0101",
      "serviceId": "plumbing",
      "serviceName": "Plumbing Repair",
      "date": "2026-01-15",
      "time": "14:00",
      "address": "1234 Palm Ave, McAllen, TX 78501",
      "city": "McAllen",
      "status": "completed",
      "price": 250,
      "paymentStatus": "paid",
      "description": "Leaky kitchen faucet replacement",
      "createdAt": "2026-01-10"
    },
    {
      "id": "BK002",
      "clientId": "CL003",
      "clientName": "Robert & Lisa Thompson",
      "clientPhone": "(956) 555-0103",
      "serviceId": "hvac",
      "serviceName": "Climate Control",
      "date": "2026-01-18",
      "time": "09:00",
      "address": "7890 Maple Dr, Mission, TX 78572",
      "city": "Mission",
      "status": "completed",
      "price": 450,
      "paymentStatus": "paid",
      "description": "AC unit inspection and filter replacement for rental property",
      "createdAt": "2026-01-14"
    },
    {
      "id": "BK003",
      "clientId": "CL005",
      "clientName": "Carlos Rodriguez",
      "clientPhone": "(956) 555-0105",
      "serviceId": "electrical",
      "serviceName": "Electrical Services",
      "date": "2026-01-22",
      "time": "10:00",
      "address": "5678 Veterans Blvd, Brownsville, TX 78520",
      "city": "Brownsville",
      "status": "completed",
      "price": 375,
      "paymentStatus": "paid",
      "description": "Rewiring master bedroom and installing new outlets",
      "createdAt": "2026-01-16"
    },
    {
      "id": "BK004",
      "clientId": "CL010",
      "clientName": "Jennifer Torres",
      "clientPhone": "(956) 555-0110",
      "serviceId": "general",
      "serviceName": "General Repair",
      "date": "2026-01-25",
      "time": "08:00",
      "address": "1234 Rio Grande St, Brownsville, TX 78520",
      "city": "Brownsville",
      "status": "scheduled",
      "price": 180,
      "paymentStatus": "deposit",
      "description": "Fix broken door hinge and repair cabinet in restaurant kitchen",
      "createdAt": "2026-01-18"
    },
    {
      "id": "BK005",
      "clientId": "CL007",
      "clientName": "David Kim",
      "clientPhone": "(956) 555-0107",
      "serviceId": "smart",
      "serviceName": "Smart Home Setup",
      "date": "2026-02-01",
      "time": "13:00",
      "address": "123 University Dr, Edinburg, TX 78539",
      "city": "Edinburg",
      "status": "new",
      "price": 650,
      "paymentStatus": "pending",
      "description": "Install smart thermostat, lighting system, and security cameras",
      "createdAt": "2026-01-20"
    },
    {
      "id": "BK006",
      "clientId": "CL003",
      "clientName": "Robert & Lisa Thompson",
      "clientPhone": "(956) 555-0103",
      "serviceId": "painting",
      "serviceName": "Interior & Exterior",
      "date": "2026-01-28",
      "time": "08:00",
      "address": "7890 Maple Dr, Mission, TX 78572",
      "city": "Mission",
      "status": "contacted",
      "price": 1200,
      "paymentStatus": "pending",
      "description": "Paint 3 bedrooms and exterior trim work",
      "createdAt": "2026-01-22"
    },
    {
      "id": "BK007",
      "clientId": "CL002",
      "clientName": "Maria Garcia",
      "clientPhone": "(956) 555-0102",
      "serviceId": "plumbing",
      "serviceName": "Plumbing Repair",
      "date": "2026-01-20",
      "time": "15:00",
      "address": "4567 Oak St, Edinburg, TX 78539",
      "city": "Edinburg",
      "status": "completed",
      "price": 150,
      "paymentStatus": "paid",
      "description": "Clogged bathroom sink drain cleaning",
      "createdAt": "2026-01-17"
    },
    {
      "id": "BK008",
      "clientId": "CL009",
      "clientName": "Texas Valley Properties LLC",
      "clientPhone": "(956) 555-0109",
      "serviceId": "hvac",
      "serviceName": "Climate Control",
      "date": "2026-01-12",
      "time": "09:00",
      "address": "7890 Business Park, Pharr, TX 78577",
      "city": "Pharr",
      "status": "cancelled",
      "price": 200,
      "paymentStatus": "refunded",
      "description": "Commercial HVAC maintenance - cancelled by client",
      "createdAt": "2026-01-08"
    },
    {
      "id": "BK009",
      "clientId": "CL008",
      "clientName": "Rosa and Miguel Hernandez",
      "clientPhone": "(956) 555-0108",
      "serviceId": "general",
      "serviceName": "General Repair",
      "date": "2026-01-12",
      "time": "10:00",
      "address": "4567 Zona Rio Rd, McAllen, TX 78501",
      "city": "McAllen",
      "status": "completed",
      "price": 95,
      "paymentStatus": "paid",
      "description": "Patch drywall and repaint small area",
      "createdAt": "2026-01-08"
    },
    {
      "id": "BK010",
      "clientId": "CL006",
      "clientName": "Sara and Tom Williams",
      "clientPhone": "(956) 555-0106",
      "serviceId": "electrical",
      "serviceName": "Electrical Services",
      "date": "2026-02-05",
      "time": "11:00",
      "address": "8901 Cypress Ln, Weslaco, TX 78595",
      "city": "Weslaco",
      "status": "new",
      "price": 280,
      "paymentStatus": "pending",
      "description": "Install ceiling fans in living room and bedroom",
      "createdAt": "2026-01-25"
    },
    {
      "id": "BK011",
      "clientId": "CL001",
      "clientName": "Juan Martinez",
      "clientPhone": "(956) 555-0101",
      "serviceId": "smart",
      "serviceName": "Smart Home Setup",
      "date": "2026-02-08",
      "time": "14:00",
      "address": "1234 Palm Ave, McAllen, TX 78501",
      "city": "McAllen",
      "status": "scheduled",
      "price": 425,
      "paymentStatus": "deposit",
      "description": "Set up smart lighting system for backyard patio",
      "createdAt": "2026-01-28"
    },
    {
      "id": "BK012",
      "clientId": "CL009",
      "clientName": "Texas Valley Properties LLC",
      "clientPhone": "(956) 555-0109",
      "serviceId": "plumbing",
      "serviceName": "Plumbing Repair",
      "date": "2026-01-30",
      "time": "09:00",
      "address": "7890 Business Park, Pharr, TX 78577",
      "city": "Pharr",
      "status": "completed",
      "price": 320,
      "paymentStatus": "paid",
      "description": "Water heater maintenance for rental property",
      "createdAt": "2026-01-24"
    },
    {
      "id": "BK013",
      "clientId": "CL004",
      "clientName": "Cindy Lopez",
      "clientPhone": "(956) 555-0104",
      "serviceId": "painting",
      "serviceName": "Interior & Exterior",
      "date": "2025-11-30",
      "time": "08:00",
      "address": "2345 Brownsville Hwy, Harlingen, TX 78550",
      "city": "Harlingen",
      "status": "completed",
      "price": 550,
      "paymentStatus": "paid",
      "description": "Paint interior of single-family home",
      "createdAt": "2025-11-20"
    },
    {
      "id": "BK014",
      "clientId": "CL005",
      "clientName": "Carlos Rodriguez",
      "clientPhone": "(956) 555-0105",
      "serviceId": "hvac",
      "serviceName": "Climate Control",
      "date": "2026-01-05",
      "time": "10:00",
      "address": "5678 Veterans Blvd, Brownsville, TX 78520",
      "city": "Brownsville",
      "status": "completed",
      "price": 500,
      "paymentStatus": "paid",
      "description": "Emergency AC repair for home",
      "createdAt": "2026-01-02"
    },
    {
      "id": "BK015",
      "clientId": "CL002",
      "clientName": "Maria Garcia",
      "clientPhone": "(956) 555-0102",
      "serviceId": "electrical",
      "serviceName": "Electrical Services",
      "date": "2026-02-10",
      "time": "13:00",
      "address": "4567 Oak St, Edinburg, TX 78539",
      "city": "Edinburg",
      "status": "new",
      "price": 220,
      "paymentStatus": "pending",
      "description": "Add additional outlets to garage workshop",
      "createdAt": "2026-02-01"
    }
  ]
}
